CaptureFile/CaptureFile.py
CaptureFile/__init__.py
CaptureFile-1.2.0.dist-info/LICENSE.md
CaptureFile-1.2.0.dist-info/METADATA
CaptureFile-1.2.0.dist-info/WHEEL
CaptureFile-1.2.0.dist-info/top_level.txt
CaptureFile-1.2.0.dist-info/RECORD
