Metadata-Version: 2.1
Name: CaptureFile
Version: 1.2.0
Summary: Transactional record logging library
Home-page: https://github.com/MIOsoft/CaptureFile-Python
Author: Bert Barabas
Author-email: bert.barabas@miosoft.com
Project-URL: Bug Tracker, https://github.com/MIOsoft/CaptureFile-Python/issues
Classifier: Programming Language :: Python :: 3
Classifier: License :: OSI Approved :: MIT License
Classifier: Operating System :: OS Independent
Classifier: Topic :: Software Development :: Libraries :: Python Modules
Requires-Python: >=3.8
License-File: LICENSE.md
